LICENSE
README.md
flypper/__init__.py
flypper/client.py
flypper/context.py
flypper/entities/__init__.py
flypper/entities/flag.py
flypper/py.typed
flypper/storage/__init__.py
flypper/storage/abstract.py
flypper/storage/in_memory.py
flypper/wsgi/__init__.py
flypper/wsgi/templates/deleted.html
flypper/wsgi/templates/edit_form.html
flypper/wsgi/templates/flags_list.html
flypper/wsgi/templates/index.html
flypper/wsgi/templates/layout.html
flypper/wsgi/web_ui.py
flypper-0.1.7.dist-info/LICENSE
flypper-0.1.7.dist-info/WHEEL
flypper-0.1.7.dist-info/METADATA
flypper-0.1.7.dist-info/RECORD
