Metadata-Version: 2.1
Name: flypper
Version: 0.1.7
Summary: Flypper is a lightweight feature flag package that ships with a WSGI interface.
Home-page: https://github.com/nicoolas25/flypper
Author: Nicolas Zermati
Author-email: nicoolas25@gmail.com
Requires-Python: >=3.7,<4.0
Classifier: Programming Language :: Python :: 3
Classifier: Programming Language :: Python :: 3.10
Classifier: Programming Language :: Python :: 3.7
Classifier: Programming Language :: Python :: 3.8
Classifier: Programming Language :: Python :: 3.9
Requires-Dist: Jinja2 (>=2.0,<4.0)
Requires-Dist: Werkzeug (>=0.16.1)
Project-URL: Documentation, https://github.com/nicoolas25/flypper
Project-URL: Repository, https://github.com/nicoolas25/flypper
